README.md
setup.py
alibabacloud_sdk_cs20151215/__init__.py
alibabacloud_sdk_cs20151215/client.py
alibabacloud_sdk_cs20151215/models.py
alibabacloud_sdk_cs20151215.egg-info/PKG-INFO
alibabacloud_sdk_cs20151215.egg-info/SOURCES.txt
alibabacloud_sdk_cs20151215.egg-info/dependency_links.txt
alibabacloud_sdk_cs20151215.egg-info/requires.txt
alibabacloud_sdk_cs20151215.egg-info/top_level.txt